baynext_cli/__init__.py
baynext_cli/config.py
baynext_cli/main.py
baynext_cli/utils.py
baynext_cli/commands/__init__.py
baynext_cli/commands/utils.py
baynext_cli/commands/config/__init__.py
baynext_cli/commands/config/get.py
baynext_cli/commands/config/set.py
baynext_cli/commands/config/show.py
baynext_cli/commands/user/__init__.py
baynext_cli/commands/user/me.py
baynext_cli-0.1.0.dist-info/METADATA
baynext_cli-0.1.0.dist-info/WHEEL
baynext_cli-0.1.0.dist-info/entry_points.txt
baynext_cli-0.1.0.dist-info/RECORD
