Metadata-Version: 2.4
Name: baynext-cli
Version: 0.1.0
Summary: The Baynext CLI lets you manage your Baynext projects directly from the terminal
Author-email: Léo Grosjean <leo.grosjean@live.fr>
Requires-Python: >=3.12
Requires-Dist: baynext-py>=0.1.0
Requires-Dist: python-dotenv>=1.1.1
Requires-Dist: typer>=0.16.0
